certifi_win32/__init__.py
certifi_win32/bootstrap.py
certifi_win32/wincerts.py
certifi_win32/wrapt_certifi.py
certifi_win32/wrapt_pip.py
python_certifi_win32-1.5.data/data/lib/site-packages/python-certifi-win32-init.pth
python_certifi_win32-1.5.dist-info/LICENSE
python_certifi_win32-1.5.dist-info/METADATA
python_certifi_win32-1.5.dist-info/WHEEL
python_certifi_win32-1.5.dist-info/top_level.txt
python_certifi_win32-1.5.dist-info/RECORD
