Metadata-Version: 2.1
Name: python-certifi-win32
Version: 1.5
Summary: Add windows certificate store to certifi cacerts.
Home-page: https://gitlab.com/alelec/python-certifi-win32
Author: Andrew Leech
Author-email: andrew.leech@planetinnovation.com.au
License: BSD
Platform: UNKNOWN
Requires-Dist: wrapt (>=1.10.4)
Requires-Dist: certifi
Requires-Dist: setuptools-scm
Requires-Dist: wincertstore ; python_version < "3.4"
